AUTHORS
COPYING
README.md
pyproject.toml
setup.py
doc/n3map-hashcatify.1
doc/n3map-johnify.1
doc/n3map-nsec3-lookup.1
doc/n3map.1
n3map/__init__.py
n3map/exception.py
n3map/hashcatify.py
n3map/johnify.py
n3map/log.py
n3map/map.py
n3map/name.py
n3map/nsec3chain.py
n3map/nsec3hash.c
n3map/nsec3lookup.py
n3map/nsec3walker.py
n3map/nsecwalker.py
n3map/predict.py
n3map/prehash.py
n3map/query.py
n3map/queryprovider.py
n3map/rrfile.py
n3map/statusline.py
n3map/util.py
n3map/vis.py
n3map/walker.py
n3map.egg-info/PKG-INFO
n3map.egg-info/SOURCES.txt
n3map.egg-info/dependency_links.txt
n3map.egg-info/entry_points.txt
n3map.egg-info/requires.txt
n3map.egg-info/top_level.txt
n3map/rrtypes/__init__.py
n3map/rrtypes/nsec.py
n3map/rrtypes/nsec3.py
n3map/rrtypes/rr.py
n3map/tree/__init__.py
n3map/tree/bstree.py
n3map/tree/nsec3tree.py
n3map/tree/rbtree.py