Metadata-Version: 2.1
Name: n3map
Version: 0.6.5
Summary: Enumerate DNS zones based on DNSSEC records
Author-email: Ralf Sager <nsec3map@3fnc.org>
License:                     GNU GENERAL PUBLIC LICENSE
Project-URL: Homepage, https://github.com/anonion0/nsec3map
Keywords: security,network,cryptography,dns,dnssec,nsec,nsec3,scanner
Classifier: Development Status :: 5 - Production/Stable
Classifier: Environment :: Console
Classifier: Intended Audience :: Developers
Classifier: Intended Audience :: Information Technology
Classifier: Intended Audience :: Science/Research
Classifier: Intended Audience :: System Administrators
Classifier: Intended Audience :: Telecommunications Industry
Classifier: License :: OSI Approved :: GNU General Public License v3 (GPLv3)
Classifier: Operating System :: POSIX
Classifier: Programming Language :: C
Classifier: Programming Language :: Python :: 3
Classifier: Topic :: Security
Classifier: Topic :: Security :: Cryptography
Classifier: Topic :: System :: Networking
Classifier: Topic :: Internet :: Name Service (DNS)
Classifier: Topic :: Internet
Requires-Python: >=3.9
Provides-Extra: predict
License-File: AUTHORS
